pp_creators/__init__.py
pp_creators/basic_creator.py
pp_creators/creator.py
pp_creators/creator_ee.py
pp_creators/error_checking_creator.py
pp_creators/utils.py
pp_creators/validators/__init__.py
pp_creators/validators/validator.py
pp_translator-0.8.0.dist-info/LICENSE
pp_translator-0.8.0.dist-info/METADATA
pp_translator-0.8.0.dist-info/WHEEL
pp_translator-0.8.0.dist-info/top_level.txt
pp_translator-0.8.0.dist-info/RECORD
